.DS_Store
.gitignore
LICENSE
README.md
README_EN.md
requirements.txt
run.py
run_oneclick.py
setup.py
submit.py
.idea/.gitignore
.idea/automl_for_competition.iml
.idea/encodings.xml
.idea/misc.xml
.idea/modules.xml
.idea/vcs.xml
.idea/inspectionProfiles/profiles_settings.xml
.idea/leetcode/editor.xml
automl_x.egg-info/PKG-INFO
automl_x.egg-info/SOURCES.txt
automl_x.egg-info/dependency_links.txt
automl_x.egg-info/not-zip-safe
automl_x.egg-info/requires.txt
automl_x.egg-info/top_level.txt
autox/__init__.py
autox/autots.py
autox/autox.py
autox/autoxserver.py
autox/autoxserver_openmldb.py
autox/main.py
autox/autox_competition/CONST.py
autox/autox_competition/README.md
autox/autox_competition/__init__.py
autox/autox_competition/util.py
autox/autox_competition/ensemble/__init__.py
autox/autox_competition/ensemble/stacking.py
autox/autox_competition/feature_engineer/README.md
autox/autox_competition/feature_engineer/__init__.py
autox/autox_competition/feature_engineer/fe_count.py
autox/autox_competition/feature_engineer/fe_cross.py
autox/autox_competition/feature_engineer/fe_cumsum.py
autox/autox_competition/feature_engineer/fe_denoising_autoencoder.py
autox/autox_competition/feature_engineer/fe_diff.py
autox/autox_competition/feature_engineer/fe_dimension_reduction.py
autox/autox_competition/feature_engineer/fe_exp_weighted_mean.py
autox/autox_competition/feature_engineer/fe_gbdt.py
autox/autox_competition/feature_engineer/fe_image2vec.py
autox/autox_competition/feature_engineer/fe_nlp.py
autox/autox_competition/feature_engineer/fe_one2M.py
autox/autox_competition/feature_engineer/fe_one2many.py
autox/autox_competition/feature_engineer/fe_rank.py
autox/autox_competition/feature_engineer/fe_rolling_stat_ts.py
autox/autox_competition/feature_engineer/fe_shift.py
autox/autox_competition/feature_engineer/fe_shift_ts.py
autox/autox_competition/feature_engineer/fe_stat.py
autox/autox_competition/feature_engineer/fe_target_encoding.py
autox/autox_competition/feature_engineer/fe_time.py
autox/autox_competition/feature_selection/README.md
autox/autox_competition/feature_selection/__init__.py
autox/autox_competition/feature_selection/adversarial_validation.py
