Metadata-Version: 2.1
Name: automl-x
Version: 0.3.0
Summary: automl tools
Home-page: https://github.com/4paradigm/autox
Author: caihengxing
Author-email: caihengxing@4paradigm.com
License: UNKNOWN
Platform: UNKNOWN
Requires-Python: >=3.6
License-File: LICENSE
